{
	"one_table": [{
		"id": "1",
		"number": "16",
		"percentage": "22",
		"class": "地方风味",
		"list": [{
			"name": "宝燕海货工场一店宁波菜",
			"lat": "31.31498858",
			"lon": "121.4987274",
			"flow": "488",
			"consume": "262",
			"class": "地方风味",
			"id": "10"
		}, {
			"name": "悦小馆",
			"lat": "31.30619852",
			"lon": "121.5128582",
			"flow": "3732",
			"consume": "79",
			"class": "地方风味",
			"id": "11"
		}, {
			"name": "小场合农家文化主题餐厅",
			"lat": "31.31632682",
			"lon": "121.5004225",
			"flow": "2547",
			"consume": "74",
			"class": "地方风味",
			"id": "12"
		}, {
			"name": "杜阿姨私房锅",
			"lat": "31.31557369",
			"lon": "121.5171283",
			"flow": "646",
			"consume": "61",
			"class": "地方风味",
			"id": "13"
		}, {
			"name": "阿虎龙虾",
			"lat": "31.31102723",
			"lon": "121.511721",
			"flow": "205",
			"consume": "152",
			"class": "地方风味",
			"id": "14"
		}, {
			"name": "陶子餐厅",
			"lat": "31.29654919",
			"lon": "121.504667",
			"flow": "70",
			"consume": "121",
			"class": "地方风味",
			"id": "15"
		}, {
			"name": "梅园春晓",
			"lat": "31.30273246",
			"lon": "121.5319855",
			"flow": "4611",
			"consume": "-",
			"class": "地方风味",
			"id": "16"
		}, {
			"name": "江南村酒家",
			"lat": "31.29901136",
			"lon": "121.5179222",
			"flow": "6082",
			"consume": "93",
			"class": "地方风味",
			"id": "17"
		}, {
			"name": "良食筷乐",
			"lat": "31.30195808",
			"lon": "121.5004357",
			"flow": "238",
			"consume": "60",
			"class": "地方风味",
			"id": "18"
		}, {
			"name": "金时代顺风大酒店",
			"lat": "31.29629249",
			"lon": "121.5062978",
			"flow": "2888",
			"consume": "128",
			"class": "地方风味",
			"id": "19"
		}, {
			"name": "METOOCATE米桃餐厅",
			"lat": "31.30910046",
			"lon": "121.5296325",
			"flow": "5007",
			"consume": "82",
			"class": "地方风味",
			"id": "20"
		}, {
			"name": "大宁948绿色私房菜",
			"lat": "31.31113723",
			"lon": "121.5196174",
			"flow": "35",
			"consume": "122",
			"class": "地方风味",
			"id": "21"
		}, {
			"name": "金盛源",
			"lat": "31.30689432",
			"lon": "121.5366847",
			"flow": "212",
			"consume": "197",
			"class": "地方风味",
			"id": "22"
		}, {
			"name": "品胜味道",
			"lat": "31.2929456",
			"lon": "121.519788",
			"flow": "1929",
			"consume": "89",
			"class": "地方风味",
			"id": "23"
		}, {
			"name": "北士大酒店中餐厅",
			"lat": "31.28708098",
			"lon": "121.520473",
			"flow": "405",
			"consume": "182",
			"class": "地方风味",
			"id": "24"
		}, {
			"name": "淮扬味道",
			"lat": "31.31190872",
			"lon": "121.4934917",
			"flow": "115",
			"consume": "101",
			"class": "地方风味",
			"id": "25"
		}, {
			"name": "宋园·金宴浙鲜馆",
			"lat": "31.3147747",
			"lon": "121.5087726",
			"flow": "556",
			"consume": "107",
			"class": "地方风味",
			"id": "26"
		}, {
			"name": "浦西洲际酒店翠庭中餐厅",
			"lat": "31.30466027",
			"lon": "121.501148",
			"flow": "349",
			"consume": "247",
			"class": "地方风味",
			"id": "27"
		}, {
			"name": "申宴酒楼",
			"lat": "31.3084682",
			"lon": "121.5061977",
			"flow": "802",
			"consume": "158",
			"class": "地方风味",
			"id": "28"
		}, {
			"name": "70后饭吧",
			"lat": "31.28706373",
			"lon": "121.4964539",
			"flow": "9530",
			"consume": "73",
			"class": "地方风味",
			"id": "29"
		}]
	}, {
		"id": "2",
		"number": "15",
		"percentage": "21",
		"class": "时尚餐厅",
		"list": [{
			"name": "成隆行蟹王府",
			"lat": "31.31273218",
			"lon": "121.5164202",
			"flow": "568",
			"consume": "422",
			"class": "时尚餐厅",
			"id": "50"
		}, {
			"name": "舟山海中洲渔社",
			"lat": "31.31823703",
			"lon": "121.5252552",
			"flow": "236",
			"consume": "258",
			"class": "时尚餐厅",
			"id": "51"
		}, {
			"name": "原烹分店",
			"lat": "31.29521067",
			"lon": "121.5009119",
			"flow": "45",
			"consume": "745",
			"class": "时尚餐厅",
			"id": "52"
		}, {
			"name": "蟹王府阳澄湖大闸蟹",
			"lat": "31.29579742",
			"lon": "121.5054609",
			"flow": "9",
			"consume": "-",
			"class": "时尚餐厅",
			"id": "53"
		}, {
			"name": "得一鲜阳澄湖大闸蟹",
			"lat": "31.29609079",
			"lon": "121.5070917",
			"flow": "5",
			"consume": "-",
			"class": "时尚餐厅",
			"id": "54"
		}, {
			"name": "陈记红膏生态大闸蟹",
			"lat": "31.29710628",
			"lon": "121.5106752",
			"flow": "5",
			"consume": "-",
			"class": "时尚餐厅",
			"id": "55"
		}, {
			"name": "蟹庄缘阳澄湖大闸蟹",
			"lat": "31.29397244",
			"lon": "121.5128357",
			"flow": "1",
			"consume": "-",
			"class": "时尚餐厅",
			"id": "56"
		}, {
			"name": "正宗昆山清水大闸蟹",
			"lat": "31.29565936",
			"lon": "121.5155823",
			"flow": "1",
			"consume": "-",
			"class": "时尚餐厅",
			"id": "57"
		}, {
			"name": "阳澄湖大闸蟹",
			"lat": "31.30027649",
			"lon": "121.5144675",
			"flow": "1",
			"consume": "-",
			"class": "时尚餐厅",
			"id": "58"
		}, {
			"name": "阳澄湖大闸蟹分店",
			"lat": "31.29038709",
			"lon": "121.5276776",
			"flow": "3",
			"consume": "-",
			"class": "时尚餐厅",
			"id": "59"
		}, {
			"name": "蟹庄缘阳澄湖大闸蟹",
			"lat": "31.28818663",
			"lon": "121.5239869",
			"flow": "5",
			"consume": "-",
			"class": "时尚餐厅",
			"id": "60"
		}, {
			"name": "阳澄湖大闸蟹",
			"lat": "31.2834538",
			"lon": "121.5230226",
			"flow": "1",
			"consume": "-",
			"class": "时尚餐厅",
			"id": "61"
		}, {
			"name": "阳澄湖大闸蟹",
			"lat": "31.28234487",
			"lon": "121.5193386",
			"flow": "1",
			"consume": "-",
			"class": "时尚餐厅",
			"id": "62"
		}, {
			"name": "富罟河豚料理",
			"lat": "31.28366524",
			"lon": "121.5141888",
			"flow": "809",
			"consume": "327",
			"class": "时尚餐厅",
			"id": "63"
		}, {
			"name": "拉麵競技館RamenArena广告",
			"lat": "31.28659932",
			"lon": "121.5157337",
			"flow": "2005",
			"consume": "69",
			"class": "时尚餐厅",
			"id": "64"
		}, {
			"name": "蟹的岡田屋",
			"lat": "31.2882745",
			"lon": "121.5095622",
			"flow": "596",
			"consume": "583",
			"class": "时尚餐厅",
			"id": "65"
		}, {
			"name": "万岛日本料理铁板烧",
			"lat": "31.29172187",
			"lon": "121.5044982",
			"flow": "2146",
			"consume": "377",
			"class": "时尚餐厅",
			"id": "66"
		}, {
			"name": "三丁目的回忆",
			"lat": "31.29141473",
			"lon": "121.4954736",
			"flow": "3602",
			"consume": "132",
			"class": "时尚餐厅",
			"id": "67"
		}, {
			"name": "YO！NiKU烧肉夜食",
			"lat": "31.29618217",
			"lon": "121.4951303",
			"flow": "1822",
			"consume": "191",
			"class": "时尚餐厅",
			"id": "68"
		}, {
			"name": "林妈妈刺身寿司",
			"lat": "31.30161185",
			"lon": "121.5016444",
			"flow": "2879",
			"consume": "117",
			"class": "时尚餐厅",
			"id": "69"
		}]
	}, {
		"id": "3",
		"number": "10",
		"percentage": "14",
		"class": "西餐",
		"list": [{
			"name": "咔萨迷娅意大利西餐厅暂停营业",
			"lat": "31.31707964",
			"lon": "121.5089257",
			"flow": "264",
			"consume": "120",
			"class": "西餐",
			"id": "80"
		}, {
			"name": "芝根芝底",
			"lat": "31.31685355",
			"lon": "121.4963055",
			"flow": "664",
			"consume": "31",
			"class": "西餐",
			"id": "81"
		}, {
			"name": "德林火锅&烤肉店",
			"lat": "31.31612028",
			"lon": "121.4933873",
			"flow": "360",
			"consume": "57",
			"class": "西餐",
			"id": "82"
		}, {
			"name": "O2ZONE氧舍",
			"lat": "31.31626693",
			"lon": "121.4910698",
			"flow": "636",
			"consume": "76",
			"class": "西餐",
			"id": "83"
		}, {
			"name": "THEGREENBISTRO绿食集",
			"lat": "31.31384709",
			"lon": "121.4927864",
			"flow": "781",
			"consume": "142",
			"class": "西餐",
			"id": "84"
		}, {
			"name": "Magnet磁石",
			"lat": "31.31062053",
			"lon": "121.4975071",
			"flow": "2564",
			"consume": "156",
			"class": "西餐",
			"id": "85"
		}, {
			"name": "雪宜茶声Nevecha",
			"lat": "31.31221298",
			"lon": "121.4897552",
			"flow": "226",
			"consume": "162",
			"class": "西餐",
			"id": "86"
		}, {
			"name": "Lilliput粒粒堡亲子餐厅",
			"lat": "31.31157384",
			"lon": "121.4929581",
			"flow": "72",
			"consume": "177",
			"class": "西餐",
			"id": "87"
		}, {
			"name": "Alma餐厅",
			"lat": "31.30944721",
			"lon": "121.5006829",
			"flow": "1835",
			"consume": "199",
			"class": "西餐",
			"id": "88"
		}, {
			"name": "西堤厚牛排",
			"lat": "31.30549875",
			"lon": "121.5017302",
			"flow": "15099",
			"consume": "163",
			"class": "西餐",
			"id": "89"
		}, {
			"name": "乐凯撒·榴莲比萨",
			"lat": "31.30871387",
			"lon": "121.4926148",
			"flow": "2373",
			"consume": "75",
			"class": "西餐",
			"id": "90"
		}, {
			"name": "PizzaMarzano玛尚诺",
			"lat": "31.31331294",
			"lon": "121.4890685",
			"flow": "828",
			"consume": "118",
			"class": "西餐",
			"id": "91"
		}, {
			"name": "Green&Tasty绿塔沙拉",
			"lat": "31.31792839",
			"lon": "121.4860177",
			"flow": "729",
			"consume": "57",
			"class": "西餐",
			"id": "92"
		}, {
			"name": "Zero零度餐厅",
			"lat": "31.32268555",
			"lon": "121.490751",
			"flow": "795",
			"consume": "78",
			"class": "西餐",
			"id": "93"
		}, {
			"name": "GelatoPiqueCafe",
			"lat": "31.29055694",
			"lon": "121.520456",
			"flow": "1565",
			"consume": "117",
			"class": "西餐",
			"id": "94"
		}, {
			"name": "UDBurger&Grill美式餐厅",
			"lat": "31.29151909",
			"lon": "121.5263716",
			"flow": "1316",
			"consume": "138",
			"class": "西餐",
			"id": "95"
		}, {
			"name": "浦西洲际酒店ECCO自助餐厅",
			"lat": "31.29291267",
			"lon": "121.5290323",
			"flow": "1424",
			"consume": "188",
			"class": "西餐",
			"id": "96"
		}, {
			"name": "DC超级英雄主题餐厅",
			"lat": "31.29766798",
			"lon": "121.5168522",
			"flow": "669",
			"consume": "104",
			"class": "西餐",
			"id": "97"
		}, {
			"name": "我们这里有鱼",
			"lat": "31.30104167",
			"lon": "121.5202854",
			"flow": "1136",
			"consume": "23",
			"class": "西餐",
			"id": "98"
		}, {
			"name": "意创Yolo",
			"lat": "31.29596214",
			"lon": "121.4944436",
			"flow": "103",
			"consume": "171",
			"class": "西餐",
			"id": "99"
		}]
	}, {
		"id": "4",
		"number": "5",
		"percentage": "7",
		"class": "东南亚风味",
		"list": [{
			"name": "520工坊爱的滋味广告",
			"lat": "31.31498858",
			"lon": "121.4987274",
			"flow": "107",
			"consume": "36",
			"class": "东南亚风味",
			"id": "30"
		}, {
			"name": "新马茶餐厅分店",
			"lat": "31.3120722",
			"lon": "121.5141886",
			"flow": "2995",
			"consume": "77",
			"class": "东南亚风味",
			"id": "31"
		}, {
			"name": "星泰泰式餐厅",
			"lat": "31.30680354",
			"lon": "121.5184157",
			"flow": "3872",
			"consume": "128",
			"class": "东南亚风味",
			"id": "32"
		}, {
			"name": "塔顶泰国时尚餐厅",
			"lat": "31.3054835",
			"lon": "121.5171283",
			"flow": "3662",
			"consume": "132",
			"class": "东南亚风味",
			"id": "33"
		}, {
			"name": "曼步城中城",
			"lat": "31.29587939",
			"lon": "121.5190155",
			"flow": "5523",
			"consume": "125",
			"class": "东南亚风味",
			"id": "34"
		}, {
			"name": "新娘惹",
			"lat": "31.29323898",
			"lon": "121.5204746",
			"flow": "820",
			"consume": "97",
			"class": "东南亚风味",
			"id": "35"
		}, {
			"name": "塔顶泰国时尚餐厅",
			"lat": "31.30671368",
			"lon": "121.5046671",
			"flow": "2977",
			"consume": "144",
			"class": "东南亚风味",
			"id": "36"
		}, {
			"name": "大茴香",
			"lat": "31.30165341",
			"lon": "121.5071562",
			"flow": "1571",
			"consume": "112",
			"class": "东南亚风味",
			"id": "37"
		}, {
			"name": "汉泰中泰融合餐厅",
			"lat": "31.2987198",
			"lon": "121.5086153",
			"flow": "22724",
			"consume": "102",
			"class": "东南亚风味",
			"id": "38"
		}, {
			"name": "默加马来西亚餐厅",
			"lat": "31.29756286",
			"lon": "121.5142959",
			"flow": "2516",
			"consume": "88",
			"class": "东南亚风味",
			"id": "39"
		}, {
			"name": "绿柠食堂",
			"lat": "31.29602608",
			"lon": "121.5156681",
			"flow": "273",
			"consume": "43",
			"class": "东南亚风味",
			"id": "40"
		}, {
			"name": "越道PHO越南餐厅",
			"lat": "31.32041627",
			"lon": "121.5079869",
			"flow": "1462",
			"consume": "61",
			"class": "东南亚风味",
			"id": "41"
		}, {
			"name": "pho13",
			"lat": "31.31499469",
			"lon": "121.5078285",
			"flow": "356",
			"consume": "105",
			"class": "东南亚风味",
			"id": "42"
		}, {
			"name": "泰满足",
			"lat": "31.31411474",
			"lon": "121.5025928",
			"flow": "441",
			"consume": "99",
			"class": "东南亚风味",
			"id": "43"
		}, {
			"name": "狮城芽笼玖巷",
			"lat": "31.31570102",
			"lon": "121.4874564",
			"flow": "1249",
			"consume": "82",
			"class": "东南亚风味",
			"id": "44"
		}, {
			"name": "融合马来西亚餐厅",
			"lat": "31.31372114",
			"lon": "121.4847956",
			"flow": "2380",
			"consume": "104",
			"class": "东南亚风味",
			"id": "45"
		}, {
			"name": "文星记海南鸡饭",
			"lat": "31.30713018",
			"lon": "121.4793757",
			"flow": "54",
			"consume": "31",
			"class": "东南亚风味",
			"id": "46"
		}, {
			"name": "星六甲",
			"lat": "31.30741457",
			"lon": "121.4906321",
			"flow": "111",
			"consume": "24",
			"class": "东南亚风味",
			"id": "47"
		}, {
			"name": "PHO東田越南粉",
			"lat": "31.30740443",
			"lon": "121.5372013",
			"flow": "244",
			"consume": "70",
			"class": "东南亚风味",
			"id": "48"
		}, {
			"name": "米多咖喱屋",
			"lat": "31.31231772",
			"lon": "121.532309",
			"flow": "226",
			"consume": "53",
			"class": "东南亚风味",
			"id": "49"
		}]
	}, {
		"id": "5",
		"number": "14",
		"percentage": "19",
		"class": "快速餐厅",
		"list": [{
			"name": "振鼎鸡",
			"lat": "31.31639863",
			"lon": "121.5183943",
			"flow": "909",
			"consume": "30",
			"class": "快速餐厅",
			"id": "200"
		}, {
			"name": "小绍兴",
			"lat": "31.32397358",
			"lon": "121.4999535",
			"flow": "469",
			"consume": "81",
			"class": "快速餐厅",
			"id": "201"
		}, {
			"name": "振鼎鸡",
			"lat": "31.32067405",
			"lon": "121.4983227",
			"flow": "356",
			"consume": "27",
			"class": "快速餐厅",
			"id": "202"
		}, {
			"name": "洪庆时尚餐厅",
			"lat": "31.30855225",
			"lon": "121.514017",
			"flow": "53",
			"consume": "65",
			"class": "快速餐厅",
			"id": "203"
		}, {
			"name": "绿手指美食广场",
			"lat": "31.32021681",
			"lon": "121.5304908",
			"flow": "128",
			"consume": "34",
			"class": "快速餐厅",
			"id": "204"
		}, {
			"name": "康师傅私房牛肉面",
			"lat": "31.30658353",
			"lon": "121.5131801",
			"flow": "207",
			"consume": "33",
			"class": "快速餐厅",
			"id": "205"
		}, {
			"name": "五福面馆",
			"lat": "31.30758819",
			"lon": "121.5016487",
			"flow": "105",
			"consume": "22",
			"class": "快速餐厅",
			"id": "206"
		}, {
			"name": "谷沙屋面铺",
			"lat": "31.31124874",
			"lon": "121.4972682",
			"flow": "320",
			"consume": "20",
			"class": "快速餐厅",
			"id": "207"
		}, {
			"name": "小阿姨小脚粽子",
			"lat": "31.2993964",
			"lon": "121.5144675",
			"flow": "524",
			"consume": "26",
			"class": "快速餐厅",
			"id": "208"
		}, {
			"name": "WOOF皮塔",
			"lat": "31.300652",
			"lon": "121.5259626",
			"flow": "519",
			"consume": "40",
			"class": "快速餐厅",
			"id": "209"
		}, {
			"name": "TOWS",
			"lat": "31.3038789",
			"lon": "121.5219286",
			"flow": "52",
			"consume": "33",
			"class": "快速餐厅",
			"id": "210"
		}, {
			"name": "一米堂粗麵馆",
			"lat": "31.30709688",
			"lon": "121.5148967",
			"flow": "303",
			"consume": "26",
			"class": "快速餐厅",
			"id": "211"
		}, {
			"name": "Momochitl美式爆米花专卖店",
			"lat": "31.31008153",
			"lon": "121.5036228",
			"flow": "1376",
			"consume": "34",
			"class": "快速餐厅",
			"id": "212"
		}, {
			"name": "蒸虾浏浏阳蒸菜",
			"lat": "31.30787542",
			"lon": "121.5001865",
			"flow": "30",
			"consume": "19",
			"class": "快速餐厅",
			"id": "213"
		}, {
			"name": "禾正楼",
			"lat": "31.30709688",
			"lon": "121.5116351",
			"flow": "2044",
			"consume": "26",
			"class": "快速餐厅",
			"id": "214"
		}, {
			"name": "捏个饺子",
			"lat": "31.29951343",
			"lon": "121.4877512",
			"flow": "67",
			"consume": "38",
			"class": "快速餐厅",
			"id": "215"
		}, {
			"name": "叫了个鸡分店",
			"lat": "31.29841941",
			"lon": "121.4911875",
			"flow": "295",
			"consume": "27",
			"class": "快速餐厅",
			"id": "216"
		}, {
			"name": "沙青SaladKing",
			"lat": "31.29213016",
			"lon": "121.5020277",
			"flow": "407",
			"consume": "40",
			"class": "快速餐厅",
			"id": "217"
		}, {
			"name": "泰煌鸡",
			"lat": "31.28963635",
			"lon": "121.503401",
			"flow": "1067",
			"consume": "34",
			"class": "快速餐厅",
			"id": "218"
		}, {
			"name": "胡记锅贴",
			"lat": "31.31741602",
			"lon": "121.5141698",
			"flow": "926",
			"consume": "13",
			"class": "快速餐厅",
			"id": "219"
		}]

	}, {
		"id": "6",
		"number": "12",
		"percentage": "13",
		"class": "西饼甜点",
		"list": [{
			"name": "哈根达斯",
			"address": "上海市共和新路1918号大宁国际商业广场一层101B室",
			"lat": "31.30212523",
			"lon": "121.5072234",
			"flow": "1732",
			"consume": "76",
			"class": "西饼甜点",
			"id": "101"
		}, {
			"name": "敢奶敢茶",
			"address": "上海市共和新路1919号",
			"lat": "31.30390187",
			"lon": "121.5114449",
			"flow": "34",
			"consume": "13",
			"class": "西饼甜点",
			"id": "102"
		}, {
			"name": "谧蜜甜品",
			"address": "上海市安业路153-155号1F",
			"lat": "31.30864665",
			"lon": "121.5058358",
			"flow": "3932",
			"consume": "40",
			"class": "西饼甜点",
			"id": "103"
		}, {
			"name": "食荳集市CHO-COLLECTOR",
			"address": "上海市西藏北路166号大悦城北区1层116单元",
			"lat": "31.30865736",
			"lon": "121.5130543",
			"flow": "373",
			"consume": "76",
			"class": "西饼甜点",
			"id": "104"
		}, {
			"name": "PONY",
			"address": "上海市西藏北路166号大悦城北区B1层",
			"lat": "31.30978289",
			"lon": "121.5333203",
			"flow": "716",
			"consume": "43",
			"class": "西饼甜点",
			"id": "105"
		}, {
			"name": "AllTheLovers分店",
			"address": "上海市万荣路777号大宁音乐广场J座1层106-107室",
			"lat": "31.31599044",
			"lon": "121.5181183",
			"flow": "802",
			"consume": "89",
			"class": "西饼甜点",
			"id": "106"
		}, {
			"name": "憶糖",
			"address": "上海市灵石路891号云仓商务A109",
			"lat": "31.31481719",
			"lon": "121.5139126",
			"flow": "278",
			"consume": "35",
			"class": "西饼甜点",
			"id": "107"
		}, {
			"name": "奉茶",
			"address": "上海市万荣路48号",
			"lat": "31.3140839",
			"lon": "121.5129684",
			"flow": "113",
			"consume": "18",
			"class": "西饼甜点",
			"id": "108"
		}, {
			"name": "PickyAllien作星人",
			"address": "上海市广中路657号",
			"lat": "31.31247063",
			"lon": "121.516745",
			"flow": "99",
			"consume": "24",
			"class": "西饼甜点",
			"id": "109"
		}, {
			"name": "纯昌老虎灶",
			"address": "上海市柳营路777号盛源生活广场1层",
			"lat": "31.30478191",
			"lon": "121.5170239",
			"flow": "87",
			"consume": "20",
			"class": "西饼甜点",
			"id": "110"
		}, {
			"name": "蔡嘉法式甜品",
			"address": "上海市万荣路700号大宁中心广场C区5栋2楼",
			"lat": "31.30832636",
			"lon": "121.484262",
			"flow": "4318",
			"consume": "131",
			"class": "西饼甜点",
			"id": "111"
		}, {
			"name": "谧蜜甜品",
			"address": "上海市万荣路699号大宁音乐广场B1层09",
			"lat": "31.31265297",
			"lon": "121.4840045",
			"flow": "743",
			"consume": "35",
			"class": "西饼甜点",
			"id": "112"
		}, {
			"name": "Coookie9",
			"address": "上海市西藏北路166号大悦城北区8层",
			"lat": "31.30313884",
			"lon": "121.48902",
			"flow": "556",
			"consume": "170",
			"class": "西饼甜点",
			"id": "113"
		}, {
			"name": "AranziCafe阿郎奇咖啡",
			"address": "上海市西藏北路166号大悦城北区六层617室",
			"lat": "31.30365831",
			"lon": "121.4946021",
			"flow": "4536",
			"consume": "71",
			"class": "西饼甜点",
			"id": "114"
		}, {
			"name": "凯司令西饼",
			"address": "上海市广中西路666号大宁小城",
			"lat": "31.30271193",
			"lon": "121.5011294",
			"flow": "854",
			"consume": "36",
			"class": "西饼甜点",
			"id": "115"
		}, {
			"name": "KOIThé",
			"address": "上海市寿阳路99号协信星光广场南区1层120号",
			"lat": "31.30667212",
			"lon": "121.5064509",
			"flow": "987",
			"consume": "23",
			"class": "西饼甜点",
			"id": "116"
		}, {
			"name": "李奥斯汀婚礼宝宝甜品桌商务茶歇...",
			"address": "上海市平型关路138号108创意广场银座101室",
			"lat": "31.30802288",
			"lon": "121.5374402",
			"flow": "97",
			"consume": "842",
			"class": "西饼甜点",
			"id": "117"
		}, {
			"name": "红宝石",
			"address": "上海市中兴路1276号",
			"lat": "31.32155401",
			"lon": "121.5194727",
			"flow": "99",
			"consume": "23",
			"class": "西饼甜点",
			"id": "120"
		}]
	}, {
		"id": "8",
		"number": "6",
		"percentage": "8",
		"class": "其它",
		"list": [{
			"name": "漢舍中国菜馆",
			"lat": "31.31338144",
			"lon": "121.5077427",
			"flow": "1324",
			"consume": "171",
			"class": "其它",
			"id": "500"
		}, {
			"name": "漢舍中国菜馆",
			"lat": "31.31799653",
			"lon": "121.5010347",
			"flow": "1324",
			"consume": "171",
			"class": "其它",
			"id": "501"
		}, {
			"name": "孔氏椒盐蛇",
			"lat": "31.31601517",
			"lon": "121.4987274",
			"flow": "444",
			"consume": "215",
			"class": "其它",
			"id": "502"
		}, {
			"name": "930私房菜",
			"lat": "31.313302",
			"lon": "121.4965816",
			"flow": "570",
			"consume": "101",
			"class": "其它",
			"id": "503"
		}, {
			"name": "莆田餐厅",
			"lat": "31.31408779",
			"lon": "121.4903746",
			"flow": "3705",
			"consume": "142",
			"class": "其它",
			"id": "504"
		}, {
			"name": "全聚德",
			"lat": "31.31672761",
			"lon": "121.4877997",
			"flow": "15174",
			"consume": "128",
			"class": "其它",
			"id": "505"
		}, {
			"name": "朵颐轩北京烤鸭",
			"lat": "31.30802209",
			"lon": "121.5007015",
			"flow": "972",
			"consume": "120",
			"class": "其它",
			"id": "506"
		}, {
			"name": "宁夏马记彭浦清真饭店分店",
			"lat": "31.30402557",
			"lon": "121.5299967",
			"flow": "787",
			"consume": "76",
			"class": "其它",
			"id": "507"
		}, {
			"name": "宏葡餐厅",
			"lat": "31.30783545",
			"lon": "121.526049",
			"flow": "855",
			"consume": "81",
			"class": "其它",
			"id": "508"
		}, {
			"name": "金唐荟",
			"lat": "31.306299",
			"lon": "121.5213278",
			"flow": "146",
			"consume": "123",
			"class": "其它",
			"id": "509"
		}, {
			"name": "SaladMando沙拉满都",
			"lat": "31.30021196",
			"lon": "121.5210703",
			"flow": "523",
			"consume": "46",
			"class": "其它",
			"id": "510"
		}, {
			"name": "有味厨道",
			"lat": "31.3037732",
			"lon": "121.4976248",
			"flow": "511",
			"consume": "86",
			"class": "其它",
			"id": "511"
		}, {
			"name": "鸡荟",
			"lat": "31.30113302",
			"lon": "121.4977106",
			"flow": "60",
			"consume": "39",
			"class": "其它",
			"id": "512"
		}, {
			"name": "清真舌尖尖牛肉面",
			"lat": "31.30136005",
			"lon": "121.5026071",
			"flow": "293",
			"consume": "27",
			"class": "其它",
			"id": "513"
		}, {
			"name": "印象徽州",
			"lat": "31.31682178",
			"lon": "121.4966674",
			"flow": "2333",
			"consume": "109",
			"class": "其它",
			"id": "514"
		}, {
			"name": "WindCafé",
			"lat": "31.30460346",
			"lon": "121.5116351",
			"flow": "93",
			"consume": "50",
			"class": "其它",
			"id": "515"
		}, {
			"name": "家宴私房菜",
			"lat": "31.31850981",
			"lon": "121.5035237",
			"flow": "229",
			"consume": "80",
			"class": "其它",
			"id": "516"
		}, {
			"name": "馋嘴烤猪蹄",
			"lat": "31.31272147",
			"lon": "121.5047386",
			"flow": "32",
			"consume": "15",
			"class": "其它",
			"id": "517"
		}, {
			"name": "匠鸭工坊·北京烤鸭",
			"lat": "31.32320867",
			"lon": "121.5193197",
			"flow": "28",
			"consume": "59",
			"class": "其它",
			"id": "518"
		}, {
			"name": "速湘食浏阳蒸菜分店",
			"lat": "31.29926716",
			"lon": "121.5307624",
			"flow": "11",
			"consume": "19",
			"class": "其它",
			"id": "519"
		}]
	}],
	"two_table": [{
		"id": "9",
		"total": "78",
		"price": "128"
	}]
}