{
	"one_table": [{
		"id": "1",
		"number": "18",
		"percentage": "5",
		"class": "数码电子",
		"list": [{
			"id": "10",
			"name": "小米之家",
			"class": "数码电子",
			"lon": "0",
			"lat": "0",
			"flow": "397",
			"consume": "1485"
		}, {
			"id": "11",
			"name": "Alienware（外星人）官方授权旗...",
			"class": "数码电子",
			"lon": "0",
			"lat": "0",
			"flow": "120",
			"consume": "23"
		}, {
			"id": "12",
			"name": "华硕体验店",
			"class": "数码电子",
			"lon": "0",
			"lat": "0",
			"flow": "43",
			"consume": "4432"
		}, {
			"id": "13",
			"name": "不夜城手机小铺",
			"class": "数码电子",
			"lon": "0",
			"lat": "0",
			"flow": "67",
			"consume": "3956"
		}, {
			"id": "14",
			"name": "苏宁电器",
			"class": "数码电子",
			"lon": "0",
			"lat": "0",
			"flow": "134",
			"consume": "5016"
		}, {
			"id": "15",
			"name": "智力苑数码",
			"class": "数码电子",
			"lon": "0",
			"lat": "0",
			"flow": "116",
			"consume": "2393"
		}, {
			"id": "16",
			"name": "国美电器",
			"class": "数码电子",
			"lon": "0",
			"lat": "0",
			"flow": "119",
			"consume": "3511"
		}, {
			"id": "17",
			"name": "大奥通讯商城",
			"class": "数码电子",
			"lon": "0",
			"lat": "0",
			"flow": "42",
			"consume": "2331"
		}, {
			"id": "18",
			"name": "友人手机",
			"class": "数码电子",
			"lon": "0",
			"lat": "0",
			"flow": "1100",
			"consume": "2572"
		}, {
			"id": "19",
			"name": "星鳗寿司手机贴膜",
			"class": "数码电子",
			"lon": "0",
			"lat": "0",
			"flow": "21",
			"consume": "18"
		}, {
			"id": "20",
			"name": "上海手机店",
			"class": "数码电子",
			"lon": "0",
			"lat": "0",
			"flow": "28",
			"consume": "3669"
		}, {
			"id": "21",
			"name": "大象科技手机网",
			"class": "数码电子",
			"lon": "0",
			"lat": "0",
			"flow": "96",
			"consume": "3553"
		}, {
			"id": "22",
			"name": "九洲在线手机商城",
			"class": "数码电子",
			"lon": "0",
			"lat": "0",
			"flow": "21",
			"consume": "4363"
		}, {
			"id": "23",
			"name": "小乔手机网",
			"class": "数码电子",
			"lon": "0",
			"lat": "0",
			"flow": "133",
			"consume": "3305"
		}, {
			"id": "24",
			"name": "夏日通讯手机专卖",
			"class": "数码电子",
			"lon": "0",
			"lat": "0",
			"flow": "98",
			"consume": "2801"
		}, {
			"id": "25",
			"name": "高蔡手机网",
			"class": "数码电子",
			"lon": "0",
			"lat": "0",
			"flow": "168",
			"consume": "3305"
		}, {
			"id": "26",
			"name": "云云手机店",
			"class": "数码电子",
			"lon": "0",
			"lat": "0",
			"flow": "217",
			"consume": "2775"
		}, {
			"id": "27",
			"name": "嘉乐数码",
			"class": "数码电子",
			"lon": "0",
			"lat": "0",
			"flow": "36",
			"consume": "2146"
		}, {
			"id": "28",
			"name": "国美电器",
			"class": "数码电子",
			"lon": "0",
			"lat": "0",
			"flow": "119",
			"consume": "3511"
		}]
	}, {
		"id": "2",
		"number": "15",
		"percentage": "5",
		"class": "个人护理",
		"list": [{
			"id": "30",
			"name": "老百姓大药房",
			"class": "个人护理",
			"lon": "0",
			"lat": "0",
			"flow": "14",
			"consume": "24"
		}, {
			"id": "31",
			"name": "复美大药房",
			"class": "个人护理",
			"lon": "0",
			"lat": "0",
			"flow": "10",
			"consume": "36"
		}, {
			"id": "32",
			"name": "布衣大药房",
			"class": "个人护理",
			"lon": "0",
			"lat": "0",
			"flow": "64",
			"consume": "81"
		}, {
			"id": "33",
			"name": "老百姓大药房",
			"class": "个人护理",
			"lon": "0",
			"lat": "0",
			"flow": "30",
			"consume": "225"
		}, {
			"id": "34",
			"name": "RE调香室",
			"class": "个人护理",
			"lon": "0",
			"lat": "0",
			"flow": "56",
			"consume": "445"
		}, {
			"id": "35",
			"name": "ISETANBEAUTY",
			"class": "个人护理",
			"lon": "0",
			"lat": "0",
			"flow": "75",
			"consume": "572"
		}, {
			"id": "36",
			"name": "innisfree",
			"class": "个人护理",
			"lon": "0",
			"lat": "0",
			"flow": "149",
			"consume": "201"
		}, {
			"id": "37",
			"name": "伊岛屋",
			"class": "个人护理",
			"lon": "0",
			"lat": "0",
			"flow": "40",
			"consume": "201"
		}, {
			"id": "38",
			"name": "屈臣氏",
			"class": "个人护理",
			"lon": "0",
			"lat": "0",
			"flow": "123",
			"consume": "127"
		}, {
			"id": "39",
			"name": "屈臣氏",
			"class": "个人护理",
			"lon": "0",
			"lat": "0",
			"flow": "160",
			"consume": "83"
		}, {
			"id": "40",
			"name": "YVESROCHER",
			"class": "个人护理",
			"lon": "0",
			"lat": "0",
			"flow": "39",
			"consume": "393"
		}, {
			"id": "41",
			"name": "美宝莲纽约",
			"class": "个人护理",
			"lon": "0",
			"lat": "0",
			"flow": "13",
			"consume": "269"
		}, {
			"id": "42",
			"name": "屈臣氏",
			"class": "个人护理",
			"lon": "0",
			"lat": "0",
			"flow": "456",
			"consume": "85"
		}, {
			"id": "43",
			"name": "freeplus",
			"class": "个人护理",
			"lon": "0",
			"lat": "0",
			"flow": "16",
			"consume": "499"
		}, {
			"id": "44",
			"name": "SEPHORA",
			"class": "个人护理",
			"lon": "0",
			"lat": "0",
			"flow": "80",
			"consume": "1787"
		}, {
			"id": "45",
			"name": "佰草集",
			"class": "个人护理",
			"lon": "0",
			"lat": "0",
			"flow": "60",
			"consume": "309"
		}]
	}, {
		"id": "3",
		"number": "8",
		"percentage": "5",
		"class": "专业美护",
		"list": [{
			"id": "50",
			"name": "天斯丽纤瘦减重养生机构",
			"class": "专业美护",
			"lon": "0",
			"lat": "0",
			"flow": "155",
			"consume": "68"
		}, {
			"id": "51",
			"name": "新氧国际皮肤管理中心",
			"class": "专业美护",
			"lon": "0",
			"lat": "0",
			"flow": "131",
			"consume": "98"
		}, {
			"id": "52",
			"name": "佰草园专业美疗美体spa",
			"class": "专业美护",
			"lon": "0",
			"lat": "0",
			"flow": "438",
			"consume": "159"
		}, {
			"id": "53",
			"name": "本真坊美容美体沙龙",
			"class": "专业美护",
			"lon": "0",
			"lat": "0",
			"flow": "885",
			"consume": "193"
		}, {
			"id": "54",
			"name": "铂菲美颜皮肤馆",
			"class": "专业美护",
			"lon": "0",
			"lat": "0",
			"flow": "94",
			"consume": "99"
		}, {
			"id": "55",
			"name": "Missha·医学抗衰老护肤SPA中心",
			"class": "专业美护",
			"lon": "0",
			"lat": "0",
			"flow": "448",
			"consume": "119"
		}, {
			"id": "56",
			"name": "仙奈SPA",
			"class": "专业美护",
			"lon": "0",
			"lat": "0",
			"flow": "195",
			"consume": "95"
		}, {
			"id": "57",
			"name": "泆美美容（培训）工作室",
			"class": "专业美护",
			"lon": "0",
			"lat": "0",
			"flow": "62",
			"consume": "241"
		}, {
			"id": "58",
			"name": "悦蓉女子专业美容养生SPA",
			"class": "专业美护",
			"lon": "0",
			"lat": "0",
			"flow": "64",
			"consume": "107"
		}]
	}, {
		"id": "4",
		"number": "10",
		"percentage": "5",
		"class": "礼品",
		"list": [{
			"id": "60",
			"name": "MistyFlower",
			"class": "礼品",
			"lon": "0",
			"lat": "0",
			"flow": "48",
			"consume": "314"
		}, {
			"id": "61",
			"name": "RigoSkyGarden天空花园分店",
			"class": "礼品",
			"lon": "0",
			"lat": "0",
			"flow": "96",
			"consume": "146"
		}, {
			"id": "62",
			"name": "VivianFlower",
			"class": "礼品",
			"lon": "0",
			"lat": "0",
			"flow": "48",
			"consume": "153"
		}, {
			"id": "63",
			"name": "韦韦花店",
			"class": "礼品",
			"lon": "0",
			"lat": "0",
			"flow": "23",
			"consume": "183"
		}, {
			"id": "64",
			"name": "鲜花花语传情",
			"class": "礼品",
			"lon": "0",
			"lat": "0",
			"flow": "4",
			"consume": "164"
		}, {
			"id": "65",
			"name": "粒上皇",
			"class": "礼品",
			"lon": "0",
			"lat": "0",
			"flow": "183",
			"consume": "35"
		}, {
			"id": "66",
			"name": "宜家瑞典食品屋",
			"class": "礼品",
			"lon": "0",
			"lat": "0",
			"flow": "62",
			"consume": "68"
		}, {
			"id": "67",
			"name": "天仁茗茶",
			"class": "礼品",
			"lon": "0",
			"lat": "0",
			"flow": "9",
			"consume": "17"
		}]
	}, {
		"id": "5",
		"number": "5",
		"percentage": "5",
		"class": "时尚家居",
		"list": [{
			"id": "70",
			"name": "大金中央空调旗舰店",
			"class": "时尚家居",
			"lon": "0",
			"lat": "0",
			"flow": "119",
			"consume": "23963"
		}, {
			"id": "71",
			"name": "朴坊",
			"class": "时尚家居",
			"lon": "0",
			"lat": "0",
			"flow": "71",
			"consume": "264"
		}, {
			"id": "72",
			"name": "生态良品",
			"class": "时尚家居",
			"lon": "0",
			"lat": "0",
			"flow": "102",
			"consume": "55"
		}, {
			"id": "73",
			"name": "上佳家具商厦",
			"class": "时尚家居",
			"lon": "0",
			"lat": "0",
			"flow": "40",
			"consume": "25533"
		}, {
			"id": "74",
			"name": "康辉整体家居",
			"class": "时尚家居",
			"lon": "0",
			"lat": "0",
			"flow": "47",
			"consume": "13920"
		}, {
			"id": "75",
			"name": "ABS家居",
			"class": "时尚家居",
			"lon": "0",
			"lat": "0",
			"flow": "8",
			"consume": "91"
		}]
	}, {
		"id": "6",
		"number": "4",
		"percentage": "5",
		"class": "产流精品",
		"list": [{
			"id": "80",
			"name": "晨光生活馆",
			"class": "产流精品",
			"lon": "0",
			"lat": "0",
			"flow": "25",
			"consume": "-"
		}, {
			"id": "81",
			"name": "BINGO",
			"class": "产流精品",
			"lon": "0",
			"lat": "0",
			"flow": "43",
			"consume": "150"
		}, {
			"id": "82",
			"name": "爱的信物馆",
			"class": "产流精品",
			"lon": "0",
			"lat": "0",
			"flow": "16",
			"consume": "-"
		}, {
			"id": "83",
			"name": "晨光文具",
			"class": "产流精品",
			"lon": "0",
			"lat": "0",
			"flow": "7",
			"consume": "-"
		}]
	}, {
		"id": "7",
		"number": "1",
		"percentage": "5",
		"class": "其他",
		"list": [{
			"id": "90",
			"name": "老北京果木烤鸭分店",
			"class": "其它",
			"lon": "0",
			"lat": "0",
			"flow": "25",
			"consume": "61"
		}]
	}],

	"two_table": [{
		"id": "9",
		"total": "10",
		"price": "50"
	}]
}